pyROGER/__init__.py
pyROGER/models.py
pyROGER/roger.py
pyROGER/dataset/HighMassRoger1_KNN.joblib
pyROGER/dataset/HighMassRoger1_RF.joblib
pyROGER/dataset/HighMassRoger1_SVM.joblib
pyROGER/dataset/__init__.py
pyROGER/dataset/highMass_testset_roger1.csv
pyROGER/dataset/highMass_trainset_roger1.csv
pyROGER/dataset/highmass_testset_roger1.csv
pyROGER/dataset/roger2_KNN.joblib
pyroger-2.0.1.dist-info/licenses/LICENSE
pyroger-2.0.1.dist-info/METADATA
pyroger-2.0.1.dist-info/WHEEL
pyroger-2.0.1.dist-info/top_level.txt
pyroger-2.0.1.dist-info/RECORD
