Metadata-Version: 2.4
Name: pyROGER
Version: 2.0.1
Summary: Implementation of ROGER in Python
Home-page:  https://github.com/martindelosrios/pyROGER
Author: Martin de los Rios
Author-email:  martindelosrios13@gmail.com 
License: The MIT License
Keywords: pyROGER,backsplash,galaxies
Classifier:  Development Status :: 4 - Beta
Classifier:  Intended Audience :: Education
Classifier:  Intended Audience :: Science/Research
Classifier:  License :: OSI Approved :: MIT License
Classifier:  Operating System :: OS Independent
Classifier:  Programming Language :: Python
Classifier:  Programming Language :: Python :: 3.8
Classifier:  Programming Language :: Python :: 3.9
Classifier:  Programming Language :: Python :: 3.10
Classifier:  Programming Language :: Python :: 3.11
Classifier:  Programming Language :: Python :: 3.12
Classifier:  Programming Language :: Python :: Implementation :: CPython
Classifier:  Topic :: Scientific/Engineering
License-File: LICENSE
Requires-Dist: numpy
Requires-Dist: matplotlib
Requires-Dist: scikit-learn
Requires-Dist: mlxtend
Requires-Dist: pandas
Requires-Dist: joblib
Dynamic: author
Dynamic: author-email
Dynamic: classifier
Dynamic: description
Dynamic: description-content-type
Dynamic: home-page
Dynamic: keywords
Dynamic: license
Dynamic: license-file
Dynamic: requires-dist
Dynamic: summary
